MANIFEST.in
setup.py
axemas/__init__.py
axemas/command.py
axemas/server.py
axemas.egg-info/PKG-INFO
axemas.egg-info/SOURCES.txt
axemas.egg-info/dependency_links.txt
axemas.egg-info/entry_points.txt
axemas.egg-info/not-zip-safe
axemas.egg-info/requires.txt
axemas.egg-info/top_level.txt
axemas/template/android/build.gradle
axemas/template/android/gradle.properties
axemas/template/android/gradlew
axemas/template/android/gradlew.bat
axemas/template/android/settings.gradle
axemas/template/android/app/build.gradle_tmpl
axemas/template/android/app/config.groovy
axemas/template/android/app/proguard-rules.pro
axemas/template/android/app/libs/empty
axemas/template/android/app/src/androidTest/java/+package_loc+/+package_company+/+package_name+/ApplicationTest.java_tmpl
axemas/template/android/app/src/main/AndroidManifest.xml_tmpl
axemas/template/android/app/src/main/assets/.empty
axemas/template/android/app/src/main/java/+package_loc+/+package_company+/+package_name+/BaseSectionController.java_tmpl
axemas/template/android/app/src/main/java/+package_loc+/+package_company+/+package_name+/IndexSectionController.java_tmpl
axemas/template/android/app/src/main/java/+package_loc+/+package_company+/+package_name+/MainActivity.java_tmpl
axemas/template/android/app/src/main/java/+package_loc+/+package_company+/+package_name+/NativeFragment.java_tmpl
axemas/template/android/app/src/main/res/drawable-hdpi/ic_launcher.png
axemas/template/android/app/src/main/res/drawable-mdpi/ic_launcher.png
axemas/template/android/app/src/main/res/drawable-mdpi/slide_icon.png
axemas/template/android/app/src/main/res/drawable-xhdpi/ic_launcher.png
axemas/template/android/app/src/main/res/drawable-xxhdpi/ic_launcher.png
axemas/template/android/app/src/main/res/layout/native_fragmet.xml
axemas/template/android/app/src/main/res/values/allert_dialog_theme.xml
axemas/template/android/app/src/main/res/values/config.xml
axemas/template/android/app/src/main/res/values/strings.xml_tmpl
axemas/template/android/app/src/main/res/values/styles.xml
axemas/template/ios/+project_id+/+project_id+-Info.plist_tmpl
axemas/template/ios/+project_id+/+project_id+-Prefix.pch
axemas/template/ios/+project_id+/AppDelegate.h
