Metadata-Version: 1.1
Name: axemas
Version: 0.0.14
Summary: Quickstart script for gearbox that setups a new mobile project using AXEMAS.
Home-page: http://axemas.readthedocs.org
Author: AXANT
Author-email: info@axant.it
License: MIT
Keywords: axemas quickstart
Platform: UNKNOWN
Classifier: Framework :: Setuptools Plugin
